WeiXueyuanCYuyanJiaocheng/README.md
WeiXueyuanCYuyanJiaocheng/__init__.py
WeiXueyuanCYuyanJiaocheng/__main__.py
WeiXueyuanCYuyanJiaocheng/file.epub
WeiXueyuanCYuyanJiaocheng/index.html
WeiXueyuanCYuyanJiaocheng/css/__init__.py
WeiXueyuanCYuyanJiaocheng/css/annotations.css
WeiXueyuanCYuyanJiaocheng/css/main.css
WeiXueyuanCYuyanJiaocheng/css/normalize.css
WeiXueyuanCYuyanJiaocheng/css/popup.css
WeiXueyuanCYuyanJiaocheng/font/__init__.py
WeiXueyuanCYuyanJiaocheng/font/fontello.eot
WeiXueyuanCYuyanJiaocheng/font/fontello.svg
WeiXueyuanCYuyanJiaocheng/font/fontello.ttf
WeiXueyuanCYuyanJiaocheng/font/fontello.woff
WeiXueyuanCYuyanJiaocheng/img/__init__.py
WeiXueyuanCYuyanJiaocheng/img/annotator-glyph-sprite.png
WeiXueyuanCYuyanJiaocheng/img/annotator-icon-sprite.png
WeiXueyuanCYuyanJiaocheng/img/apple-touch-icon.png
WeiXueyuanCYuyanJiaocheng/img/cancelfullscreen.png
WeiXueyuanCYuyanJiaocheng/img/close.png
WeiXueyuanCYuyanJiaocheng/img/fullscreen.png
WeiXueyuanCYuyanJiaocheng/img/loader.gif
WeiXueyuanCYuyanJiaocheng/img/menu-icon.png
WeiXueyuanCYuyanJiaocheng/img/save.png
WeiXueyuanCYuyanJiaocheng/img/saved.png
WeiXueyuanCYuyanJiaocheng/img/settings-s.png
WeiXueyuanCYuyanJiaocheng/img/settings.png
WeiXueyuanCYuyanJiaocheng/img/star.png
WeiXueyuanCYuyanJiaocheng/js/__init__.py
WeiXueyuanCYuyanJiaocheng/js/epub.js
WeiXueyuanCYuyanJiaocheng/js/epub.min.js
WeiXueyuanCYuyanJiaocheng/js/epub.min.map
WeiXueyuanCYuyanJiaocheng/js/hooks.min.js
WeiXueyuanCYuyanJiaocheng/js/hooks.min.map
WeiXueyuanCYuyanJiaocheng/js/reader.js
WeiXueyuanCYuyanJiaocheng/js/reader.js.map
WeiXueyuanCYuyanJiaocheng/js/reader.min.js
WeiXueyuanCYuyanJiaocheng/js/reader.min.map
WeiXueyuanCYuyanJiaocheng/js/hooks/__init__.py
WeiXueyuanCYuyanJiaocheng/js/hooks/extensions/__init__.py
WeiXueyuanCYuyanJiaocheng/js/hooks/extensions/highlight.js
WeiXueyuanCYuyanJiaocheng/js/libs/__init__.py
WeiXueyuanCYuyanJiaocheng/js/libs/jquery.min.js
WeiXueyuanCYuyanJiaocheng/js/libs/localforage.min.js
wei_xueyuan_c_yuyan_jiaocheng-2024.3.6.0.dist-info/METADATA
wei_xueyuan_c_yuyan_jiaocheng-2024.3.6.0.dist-info/WHEEL
wei_xueyuan_c_yuyan_jiaocheng-2024.3.6.0.dist-info/entry_points.txt
wei_xueyuan_c_yuyan_jiaocheng-2024.3.6.0.dist-info/top_level.txt
wei_xueyuan_c_yuyan_jiaocheng-2024.3.6.0.dist-info/RECORD
